python_project_template_AS/__init__.py
python_project_template_AS/calculator.py
python_project_template_AS/exceptions.py
python_project_template_AS/operations.py
python_project_template_AS/registry.py
python_project_template_AS/utils.py
python_project_template_as-0.1.3.dist-info/METADATA
python_project_template_as-0.1.3.dist-info/WHEEL
python_project_template_as-0.1.3.dist-info/RECORD
