Metadata-Version: 2.4
Name: python-project-template-AS
Version: 0.1.3
Summary: A minimal Python project demonstrating best practices for testing, documentation, and CI/CD. It implements a mini calculator as a minimal example.
Project-URL: Homepage, https://github.com/andreascaglioni/python-project-template
Author-email: Andrea Scaglioni <andrea.c.scaglioni@gmail.com>
License: MIT
Keywords: CI/CD,example,project-template,pytest,sphinx,template
Classifier: License :: OSI Approved :: MIT License
Classifier: Operating System :: OS Independent
Classifier: Programming Language :: Python :: 3
Requires-Python: >=3.8
Provides-Extra: dev
Requires-Dist: black; extra == 'dev'
Requires-Dist: mypy; extra == 'dev'
Requires-Dist: pre-commit; extra == 'dev'
Requires-Dist: pytest; extra == 'dev'
Requires-Dist: pytest-cov; extra == 'dev'
Requires-Dist: ruff; extra == 'dev'
Provides-Extra: docs
Requires-Dist: pydata-sphinx-theme; extra == 'docs'
Requires-Dist: sphinx-autodoc-typehints; extra == 'docs'
Requires-Dist: sphinx-copybutton; extra == 'docs'
Requires-Dist: sphinx-mdinclude; extra == 'docs'
Requires-Dist: sphinx>=7.0; extra == 'docs'
Requires-Dist: sphinxcontrib-spelling; extra == 'docs'
